aisc/__init__.py
aisc/url.py
aisc-0.1.10.dist-info/WHEEL
aisc-0.1.10.dist-info/METADATA
aisc-0.1.10.dist-info/RECORD
