Metadata-Version: 2.1
Name: aisc
Version: 0.1.10
Summary: AISC Helper Tools
Home-page: https://github.com/a1sc/aisc_tools
License: MIT
Author: MB
Author-email: mb@aisc.io
Requires-Python: >=3.7,<4.0
Classifier: License :: OSI Approved :: MIT License
Classifier: Programming Language :: Python :: 3
Classifier: Programming Language :: Python :: 3.7
Requires-Dist: requests (>=2.22,<3.0)
